colby/cb.py
colby/init.py
colby-0.2.0.dist-info/LICENSE.txt
colby-0.2.0.dist-info/METADATA
colby-0.2.0.dist-info/WHEEL
colby-0.2.0.dist-info/top_level.txt
colby-0.2.0.dist-info/RECORD
